cornice_swagger/__init__.py
cornice_swagger/swagger.py
cornice_swagger/util.py
cornice_swagger/views.py
cornice_swagger/converters/__init__.py
cornice_swagger/converters/exceptions.py
cornice_swagger/converters/parameters.py
cornice_swagger/converters/schema.py
cornice_swagger/templates/index.html
cornice_swagger/templates/index_script_template.html
tests/__init__.py
tests/support.py
tests/test_app.py
tests/test_definition_handler.py
tests/test_parameter_handler.py
tests/test_response_handler.py
tests/test_swagger.py
tests/converters/__init__.py
tests/converters/test_parameters.py
tests/converters/test_schema.py
cornice_swagger-1.0.1.dist-info/LICENSE
cornice_swagger-1.0.1.dist-info/METADATA
cornice_swagger-1.0.1.dist-info/WHEEL
cornice_swagger-1.0.1.dist-info/top_level.txt
cornice_swagger-1.0.1.dist-info/RECORD
