Metadata-Version: 2.1
Name: cornice-swagger
Version: 1.0.1
Summary: Generate swagger from a Cornice application
Home-page: https://github.com/Cornices/cornice.ext.swagger
Author: Josip Delic
Author-email: delijati@gmx.net
License: Apache License (2.0)
Keywords: web services
Platform: UNKNOWN
Classifier: License :: OSI Approved :: Apache Software License
Classifier: Programming Language :: Python
Classifier: Programming Language :: Python :: 3
Classifier: Programming Language :: Python :: 3.5
Classifier: Programming Language :: Python :: 3.6
Classifier: Programming Language :: Python :: 3.7
Classifier: Programming Language :: Python :: 3.8
License-File: LICENSE
Requires-Dist: six
Requires-Dist: cornice
Requires-Dist: colander
